expando.py
xo.py
expando-0.5.5.1.dist-info/METADATA
expando-0.5.5.1.dist-info/WHEEL
expando-0.5.5.1.dist-info/entry_points.txt
expando-0.5.5.1.dist-info/top_level.txt
expando-0.5.5.1.dist-info/RECORD
